MANIFEST.in
setup.py
tpt/FileMaker.py
tpt/Logger.py
tpt/Parser.py
tpt/TDJDBC.py
tpt/TPT.py
tpt/TPTCMD.py
tpt/TPTSQL.py
tpt/Unit_Test.py
tpt/__init__.py
tpt/iniParser.py
tpt/keywords.txt
tpt/settings.py
tpt/tbuild.py
tpt.egg-info/PKG-INFO
tpt.egg-info/SOURCES.txt
tpt.egg-info/dependency_links.txt
tpt.egg-info/requires.txt
tpt.egg-info/top_level.txt
tpt.egg-info/zip-safe