Metadata-Version: 1.0
Name: tpt
Version: 0.13
Summary: The TPT load and export simple API
Home-page: https://github.paypal.com/lihzhang/TPT-Load
Author: Zhang Lihui
Author-email: lihzhang@paypal.com
License: GNU
Platform: UNKNOWN
